k8090/__init__.py
k8090/relay_card.py
k8090-1.0.0.dist-info/LICENSE
k8090-1.0.0.dist-info/METADATA
k8090-1.0.0.dist-info/WHEEL
k8090-1.0.0.dist-info/top_level.txt
k8090-1.0.0.dist-info/RECORD
