Metadata-Version: 2.1
Name: k8090
Version: 1.0.0
Summary: A class for interacting with K8090 or VM8090 relay boards
Author-email: Morten Hauan <morten@hauan.me>
License: MIT License        
Project-URL: Homepage, https://github.com/mortenhauan/k8090
Project-URL: Bug Tracker, https://github.com/mortenhauan/k8090/issues
Classifier: Programming Language :: Python :: 3
Classifier: License :: OSI Approved :: MIT License
Classifier: Operating System :: OS Independent
Requires-Python: >=3.7
License-File: LICENSE
